Metadata-Version: 2.4
Name: file-prompt-cli
Version: 0.1.12
Summary: A CLI tool for processing files through LLMs using GCP and Gemini API
Author-email: Brian Legarth <legarth7@gmail.com>
License: MIT
Project-URL: Homepage, https://github.com/legarth7/file_prompt_cli
Project-URL: Bug-Tracker, https://github.com/legarth7/file_prompt_cli/issues
Project-URL: Source, https://github.com/legarth7/file_prompt_cli
Project-URL: Documentation, https://github.com/legarth7/file_prompt_cli#readme
Keywords: gcp,gemini,llm,cli,file-processing
Classifier: Development Status :: 4 - Beta
Classifier: Intended Audience :: Developers
Classifier: License :: OSI Approved :: MIT License
Classifier: Operating System :: OS Independent
Classifier: Programming Language :: Python :: 3
Classifier: Programming Language :: Python :: 3.8
Classifier: Programming Language :: Python :: 3.9
Classifier: Programming Language :: Python :: 3.10
Classifier: Programming Language :: Python :: 3.11
Classifier: Topic :: Software Development :: Libraries :: Python Modules
Requires-Python: >=3.8
License-File: LICENSE
Requires-Dist: google-cloud-storage>=2.0.0
Requires-Dist: google-cloud-pubsub>=2.0.0
Requires-Dist: google-cloud-secret-manager>=2.0.0
Requires-Dist: python-dotenv>=0.19.0
Requires-Dist: typer>=0.9.0
Requires-Dist: rich>=13.0.0
Provides-Extra: dev
Requires-Dist: pytest>=6.0.0; extra == "dev"
Requires-Dist: pytest-cov>=2.0.0; extra == "dev"
Requires-Dist: black>=23.7.0; extra == "dev"
Requires-Dist: isort>=5.12.0; extra == "dev"
Requires-Dist: flake8>=6.1.0; extra == "dev"
Requires-Dist: mypy>=1.5.0; extra == "dev"
Dynamic: license-file
